<annotation>
	<folder>3</folder>
	<filename>013961.jpg</filename>
	<path>C:\Users\admin\Desktop\3\013961.jpg</path>
	<source>
		<database>Unknown</database>
	</source>
	<size>
		<width>224</width>
		<height>224</height>
		<depth>3</depth>
	</size>
	<segmented>0</segmented>
	<object>
		<name>normal</name>
		<pose>Unspecified</pose>
		<truncated>0</truncated>
		<difficult>0</difficult>
		<bndbox>
			<xmin>28</xmin>
			<ymin>32</ymin>
			<xmax>83</xmax>
			<ymax>83</ymax>
		</bndbox>
	</object>
	<object>
		<name>normal</name>
		<pose>Unspecified</pose>
		<truncated>0</truncated>
		<difficult>0</difficult>
		<bndbox>
			<xmin>3</xmin>
			<ymin>105</ymin>
			<xmax>57</xmax>
			<ymax>142</ymax>
		</bndbox>
	</object>
	<object>
		<name>normal</name>
		<pose>Unspecified</pose>
		<truncated>1</truncated>
		<difficult>0</difficult>
		<bndbox>
			<xmin>179</xmin>
			<ymin>140</ymin>
			<xmax>224</xmax>
			<ymax>174</ymax>
		</bndbox>
	</object>
	<object>
		<name>normal</name>
		<pose>Unspecified</pose>
		<truncated>0</truncated>
		<difficult>0</difficult>
		<bndbox>
			<xmin>119</xmin>
			<ymin>11</ymin>
			<xmax>155</xmax>
			<ymax>63</ymax>
		</bndbox>
	</object>
</annotation>
