<annotation>
	<folder>1</folder>
	<filename>fall_340.jpg</filename>
	<path>C:\Users\17136\Desktop\1\fall_340.jpg</path>
	<source>
		<database>Unknown</database>
	</source>
	<size>
		<width>224</width>
		<height>224</height>
		<depth>3</depth>
	</size>
	<segmented>0</segmented>
	<object>
		<name>normal</name>
		<pose>Unspecified</pose>
		<truncated>0</truncated>
		<difficult>0</difficult>
		<bndbox>
			<xmin>17</xmin>
			<ymin>37</ymin>
			<xmax>75</xmax>
			<ymax>83</ymax>
		</bndbox>
	</object>
	<object>
		<name>normal</name>
		<pose>Unspecified</pose>
		<truncated>0</truncated>
		<difficult>0</difficult>
		<bndbox>
			<xmin>12</xmin>
			<ymin>103</ymin>
			<xmax>57</xmax>
			<ymax>139</ymax>
		</bndbox>
	</object>
	<object>
		<name>fall</name>
		<pose>Unspecified</pose>
		<truncated>0</truncated>
		<difficult>0</difficult>
		<bndbox>
			<xmin>102</xmin>
			<ymin>56</ymin>
			<xmax>159</xmax>
			<ymax>135</ymax>
		</bndbox>
	</object>
</annotation>
